bitrev/bitrev.v
module bitrev (
  input  sck,
  input  ss,
  input  mosi,
  output miso
);

  // State machine states
  localparam IDLE     = 2'b00;
  localparam RECEIVE  = 2'b01;
  localparam TRANSMIT = 2'b10;

  // Registers
  reg [1:0]  state;
  reg [2:0]  bit_cnt;      
  reg [7:0]  rx_data;      
  reg [7:0]  tx_data;      
  reg        miso_reg;

  wire [7:0] reversed_data_next;
  assign reversed_data_next = {rx_data[0], rx_data[1], rx_data[2], rx_data[3], 
                               rx_data[4], rx_data[5], rx_data[6], rx_data[7]};

  // Output assignment
  assign miso = miso_reg ;
  reg test;
  always @(posedge sck) begin
    test <= mosi;
  end

  always @(posedge sck or posedge ss) begin
    if (ss) begin
      state <= IDLE;
      bit_cnt <= 3'b0;
      miso_reg <= 1'b1;  // MISO high when idle
    end else begin
      case (state)
        IDLE: begin
          rx_data <= {rx_data[6:0], mosi};
          state <= RECEIVE;
          bit_cnt <= 3'b1;  
          miso_reg <= 1'b1; 
        end

        RECEIVE: begin
          // Shift in data from MOSI (MSB first)
          if (bit_cnt == 3'd7) begin
            state <= TRANSMIT;
            bit_cnt <= 3'b0;
            rx_data <= {rx_data[6:0], mosi};
            tx_data <= reversed_data_next;  // Load reversed data (including current bit)
            miso_reg <= reversed_data_next[6]; // Output MSB first
            $display("mosi: %b, rx_data: %b, tx_data: %b", mosi, rx_data, reversed_data_next);
          end else if (bit_cnt == 3'd6) begin
            miso_reg <= mosi;
            rx_data <= {rx_data[6:0], mosi};
            bit_cnt <= bit_cnt + 1'b1;
          end
            else begin
            rx_data <= {rx_data[6:0], mosi};
            bit_cnt <= bit_cnt + 1'b1;
          end
        end

        TRANSMIT: begin
          if (bit_cnt == 3'd6) begin
            state <= IDLE;
            rx_data <= 8'b0;
            bit_cnt <= 3'b0;
            miso_reg <= 1'b1;  // Set MISO high when done
          end else begin
            bit_cnt <= bit_cnt + 1'b1;
            tx_data <= {1'b0,tx_data[5:0], 1'b0};  // Shift left
            miso_reg <= tx_data[5];  // Output next bit
          end
        end

        default: begin
          state <= IDLE;
          miso_reg <= 1'b1;
        end
      endcase
    end
  end

endmodule

bitrev/bitrev.vcd
$version Generated by VerilatedVcd $end
$timescale 1ps $end
 $scope module TOP $end
  $var wire 1 ) sck $end
  $var wire 1 * ss $end
  $var wire 1 + mosi $end
  $var wire 1 , miso $end
  $scope module bitrev $end
   $var wire 1 ) sck $end
   $var wire 1 * ss $end
   $var wire 1 + mosi $end
   $var wire 1 , miso $end
   $var wire 2 . IDLE [1:0] $end
   $var wire 2 / RECEIVE [1:0] $end
   $var wire 2 0 TRANSMIT [1:0] $end
   $var wire 2 # state [1:0] $end
   $var wire 3 $ bit_cnt [2:0] $end
   $var wire 8 % rx_data [7:0] $end
   $var wire 8 & tx_data [7:0] $end
   $var wire 1 ' miso_reg $end
   $var wire 8 ( reversed_data_next [7:0] $end
   $var wire 1 - test $end
  $upscope $end
 $upscope $end
$enddefinitions $end


#0
b00 #
b000 $
b00000000 %
b00000000 &
0'
b00000000 (
0)
1*
0+
0,
0-
b00 .
b01 /
b10 0
#1
1'
1)
1,
#2
0)
#3
1)
#4
0)
#5
1)
#6
0)
#7
1)
#8
0)
#9
1)
#10
0)
#11
0*
#12
1+
#13
b01 #
b001 $
b00000001 %
b10000000 (
1)
1-
#14
0)
0+
#15
b010 $
b00000010 %
b01000000 (
1)
0-
#16
0)
1+
#17
b011 $
b00000101 %
b10100000 (
1)
1-
#18
0)
0+
#19
b100 $
b00001010 %
b01010000 (
1)
0-
#20
0)
#21
b101 $
b00010100 %
b00101000 (
1)
#22
0)
1+
#23
b110 $
b00101001 %
b10010100 (
1)
1-
#24
0)
0+
#25
b111 $
b01010010 %
0'
b01001010 (
1)
0,
0-
#26
0)
1+
#27
b10 #
b000 $
b10100101 %
b01001010 &
1'
b10100101 (
1)
1,
1-
#28
0)
0+
#29
b001 $
b00010100 &
0'
1)
0,
0-
#30
0)
#31
b010 $
b00101000 &
1)
#32
0)
#33
b011 $
b01010000 &
1'
1)
1,
#34
0)
#35
b100 $
b00100000 &
0'
1)
0,
#36
0)
#37
b101 $
b01000000 &
1'
1)
1,
#38
0)
#39
b110 $
b00000000 &
0'
1)
0,
#40
0)
#41
b00 #
b000 $
b00000000 %
1'
b00000000 (
1)
1,
#42
0)
#43
b01 #
b001 $
1)
#44
0)
#45
b010 $
1)
#46
0)
#47
b011 $
1)
#48
0)
#49
b100 $
1)
#50
0)
#51
b101 $
1)
#52
0)
#53
b110 $
1)
#54
0)
#55
b111 $
0'
1)
0,
#56
0)
#57
b10 #
b000 $
1)
#58
0)
#59
b001 $
1)
#60
b00 #
b000 $
1'
1*
1,
